simple_md2html/__init__.py
simple_md2html/__main__.py
simple_md2html/md2html.py
simple_md2html-0.0.1.dist-info/licenses/LICENSE
simple_md2html-0.0.1.dist-info/METADATA
simple_md2html-0.0.1.dist-info/WHEEL
simple_md2html-0.0.1.dist-info/top_level.txt
simple_md2html-0.0.1.dist-info/RECORD
