Metadata-Version: 2.4
Name: simple_md2html
Version: 0.0.1
Summary: a very simple python package to convert markdown document into html document.
Author-email: GGN_2015 <premierbob@qq.com>
License: MIT License
Requires-Python: >=3.11
License-File: LICENSE
Requires-Dist: markdown2
Dynamic: license-file
